[
  {
    "date": "2020-02-21T05:00:00.000Z",
    "spot": 1209.15
  },
  {
    "date": "2020-02-12T05:00:00.000Z",
    "spot": 1179.55
  },
  {
    "date": "2020-02-03T05:00:00.000Z",
    "spot": 1194.9
  },
  {
    "date": "2020-01-23T05:00:00.000Z",
    "spot": 1168.65
  },
  {
    "date": "2020-01-14T05:00:00.000Z",
    "spot": 1156.1
  },
  {
    "date": "2020-01-03T05:00:00.000Z",
    "spot": 1166.9
  },
  {
    "date": "2019-12-25T05:00:00.000Z",
    "spot": 0
  },
  {
    "date": "2019-12-16T05:00:00.000Z",
    "spot": 1172.25
  },
  {
    "date": "2019-12-05T05:00:00.000Z",
    "spot": 1190.35
  },
  {
    "date": "2019-11-26T05:00:00.000Z",
    "spot": 1176.25
  },
  {
    "date": "2019-11-15T05:00:00.000Z",
    "spot": 1166.75
  },
  {
    "date": "2019-11-06T05:00:00.000Z",
    "spot": 1156.9
  },
  {
    "date": "2019-10-28T04:00:00.000Z",
    "spot": 1170.7
  },
  {
    "date": "2019-10-17T04:00:00.000Z",
    "spot": 1186.95
  },
  {
    "date": "2019-10-08T04:00:00.000Z",
    "spot": 1193.2
  },
  {
    "date": "2019-09-27T04:00:00.000Z",
    "spot": 1199.95
  },
  {
    "date": "2019-09-18T04:00:00.000Z",
    "spot": 1191.2
  },
  {
    "date": "2019-09-09T04:00:00.000Z",
    "spot": 1193.15
  },
  {
    "date": "2019-08-29T04:00:00.000Z",
    "spot": 1216.4
  },
  {
    "date": "2019-08-20T04:00:00.000Z",
    "spot": 1208.25
  },
  {
    "date": "2019-08-09T04:00:00.000Z",
    "spot": 1210
  },
  {
    "date": "2019-07-31T04:00:00.000Z",
    "spot": 1183.05
  },
  {
    "date": "2019-07-22T04:00:00.000Z",
    "spot": 1178.35
  },
  {
    "date": "2019-07-11T04:00:00.000Z",
    "spot": 1173.5
  },
  {
    "date": "2019-07-02T04:00:00.000Z",
    "spot": 1166.05
  },
  {
    "date": "2019-06-21T04:00:00.000Z",
    "spot": 1163.9
  },
  {
    "date": "2019-06-12T04:00:00.000Z",
    "spot": 1182.75
  },
  {
    "date": "2019-06-03T04:00:00.000Z",
    "spot": 1182.15
  },
  {
    "date": "2019-05-23T04:00:00.000Z",
    "spot": 1189.15
  },
  {
    "date": "2019-05-14T04:00:00.000Z",
    "spot": 1189.4
  },
  {
    "date": "2019-05-03T04:00:00.000Z",
    "spot": 1169.8
  },
  {
    "date": "2019-04-24T04:00:00.000Z",
    "spot": 1150.75
  },
  {
    "date": "2019-04-15T04:00:00.000Z",
    "spot": 1133.05
  },
  {
    "date": "2019-04-04T04:00:00.000Z",
    "spot": 1136.35
  },
  {
    "date": "2019-03-26T04:00:00.000Z",
    "spot": 1133.5
  },
  {
    "date": "2019-03-15T04:00:00.000Z",
    "spot": 1137.1
  },
  {
    "date": "2019-03-06T05:00:00.000Z",
    "spot": 1128.8
  },
  {
    "date": "2019-02-25T05:00:00.000Z",
    "spot": 1121.05
  },
  {
    "date": "2019-02-14T05:00:00.000Z",
    "spot": 1125.3
  },
  {
    "date": "2019-02-05T05:00:00.000Z",
    "spot": 0
  },
  {
    "date": "2019-01-25T05:00:00.000Z",
    "spot": 1121.25
  },
  {
    "date": "2019-01-16T05:00:00.000Z",
    "spot": 1120.2
  },
  {
    "date": "2019-01-07T05:00:00.000Z",
    "spot": 1118.7
  },
  {
    "date": "2018-12-27T05:00:00.000Z",
    "spot": 1120.25
  },
  {
    "date": "2018-12-18T05:00:00.000Z",
    "spot": 1130
  },
  {
    "date": "2018-12-07T05:00:00.000Z",
    "spot": 1119.7
  },
  {
    "date": "2018-11-28T05:00:00.000Z",
    "spot": 1126.55
  },
  {
    "date": "2018-11-19T05:00:00.000Z",
    "spot": 1128.6
  },
  {
    "date": "2018-11-08T05:00:00.000Z",
    "spot": 1116.75
  },
  {
    "date": "2018-10-30T04:00:00.000Z",
    "spot": 1139.25
  },
  {
    "date": "2018-10-19T04:00:00.000Z",
    "spot": 1132.1
  },
  {
    "date": "2018-10-10T04:00:00.000Z",
    "spot": 1133.9
  },
  {
    "date": "2018-10-01T04:00:00.000Z",
    "spot": 1111.7
  },
  {
    "date": "2018-09-20T04:00:00.000Z",
    "spot": 1120.45
  },
  {
    "date": "2018-09-11T04:00:00.000Z",
    "spot": 1125.4
  },
  {
    "date": "2018-08-31T04:00:00.000Z",
    "spot": 1112.9
  },
  {
    "date": "2018-08-22T04:00:00.000Z",
    "spot": 1119
  },
  {
    "date": "2018-08-13T04:00:00.000Z",
    "spot": 1134.05
  },
  {
    "date": "2018-08-02T04:00:00.000Z",
    "spot": 1126.1
  },
  {
    "date": "2018-07-24T04:00:00.000Z",
    "spot": 1135.15
  },
  {
    "date": "2018-07-13T04:00:00.000Z",
    "spot": 1123.45
  },
  {
    "date": "2018-07-04T04:00:00.000Z",
    "spot": 1114.55
  },
  {
    "date": "2018-06-25T04:00:00.000Z",
    "spot": 1117.15
  },
  {
    "date": "2018-06-14T04:00:00.000Z",
    "spot": 1083.05
  },
  {
    "date": "2018-06-05T04:00:00.000Z",
    "spot": 1070.85
  },
  {
    "date": "2018-05-25T04:00:00.000Z",
    "spot": 1077.9
  },
  {
    "date": "2018-05-16T04:00:00.000Z",
    "spot": 1077.8
  },
  {
    "date": "2018-05-07T04:00:00.000Z",
    "spot": 0
  },
  {
    "date": "2018-04-26T04:00:00.000Z",
    "spot": 1080.9
  },
  {
    "date": "2018-04-17T04:00:00.000Z",
    "spot": 1067.1
  },
  {
    "date": "2018-04-06T04:00:00.000Z",
    "spot": 1069.7
  },
  {
    "date": "2018-03-28T04:00:00.000Z",
    "spot": 1070.7
  },
  {
    "date": "2018-03-19T04:00:00.000Z",
    "spot": 1071.55
  },
  {
    "date": "2018-03-08T05:00:00.000Z",
    "spot": 1070.25
  },
  {
    "date": "2018-02-27T05:00:00.000Z",
    "spot": 1071.25
  },
  {
    "date": "2018-02-16T05:00:00.000Z",
    "spot": 0
  },
  {
    "date": "2018-02-07T05:00:00.000Z",
    "spot": 1086.6
  },
  {
    "date": "2018-01-29T05:00:00.000Z",
    "spot": 1065.5
  },
  {
    "date": "2018-01-18T05:00:00.000Z",
    "spot": 1070.5
  },
  {
    "date": "2018-01-09T05:00:00.000Z",
    "spot": 1067.1
  },
  {
    "date": "2017-12-29T05:00:00.000Z",
    "spot": 0
  },
  {
    "date": "2017-12-20T05:00:00.000Z",
    "spot": 1080.9
  },
  {
    "date": "2017-12-11T05:00:00.000Z",
    "spot": 1092.2
  },
  {
    "date": "2017-11-30T05:00:00.000Z",
    "spot": 1088.05
  },
  {
    "date": "2017-11-21T05:00:00.000Z",
    "spot": 1095.9
  },
  {
    "date": "2017-11-10T05:00:00.000Z",
    "spot": 1117.05
  },
  {
    "date": "2017-11-01T04:00:00.000Z",
    "spot": 1114.4
  },
  {
    "date": "2017-10-23T04:00:00.000Z",
    "spot": 1130.25
  },
  {
    "date": "2017-10-12T04:00:00.000Z",
    "spot": 1133.15
  },
  {
    "date": "2017-10-03T04:00:00.000Z",
    "spot": 0
  },
  {
    "date": "2017-09-22T04:00:00.000Z",
    "spot": 1136.7
  },
  {
    "date": "2017-09-13T04:00:00.000Z",
    "spot": 1128.4
  },
  {
    "date": "2017-09-04T04:00:00.000Z",
    "spot": 1132.7
  },
  {
    "date": "2017-08-24T04:00:00.000Z",
    "spot": 1127.85
  },
  {
    "date": "2017-08-15T04:00:00.000Z",
    "spot": 0
  },
  {
    "date": "2017-08-04T04:00:00.000Z",
    "spot": 1124.9
  },
  {
    "date": "2017-07-26T04:00:00.000Z",
    "spot": 1121.8
  },
  {
    "date": "2017-07-17T04:00:00.000Z",
    "spot": 1128.3
  },
  {
    "date": "2017-07-06T04:00:00.000Z",
    "spot": 1157.4
  },
  {
    "date": "2017-06-27T04:00:00.000Z",
    "spot": 1137
  },
  {
    "date": "2017-06-16T04:00:00.000Z",
    "spot": 1134.2
  },
  {
    "date": "2017-06-07T04:00:00.000Z",
    "spot": 1124.05
  },
  {
    "date": "2017-05-29T04:00:00.000Z",
    "spot": 1122
  },
  {
    "date": "2017-05-18T04:00:00.000Z",
    "spot": 1124.5
  },
  {
    "date": "2017-05-09T04:00:00.000Z",
    "spot": 0
  },
  {
    "date": "2017-04-28T04:00:00.000Z",
    "spot": 1137.8
  },
  {
    "date": "2017-04-19T04:00:00.000Z",
    "spot": 1140.18
  },
  {
    "date": "2017-04-10T04:00:00.000Z",
    "spot": 1142.3
  },
  {
    "date": "2017-03-30T04:00:00.000Z",
    "spot": 1117.32
  },
  {
    "date": "2017-03-21T04:00:00.000Z",
    "spot": 1120.85
  },
  {
    "date": "2017-03-10T05:00:00.000Z",
    "spot": 1157.38
  },
  {
    "date": "2017-03-01T05:00:00.000Z",
    "spot": 0
  },
  {
    "date": "2017-02-20T05:00:00.000Z",
    "spot": 1147.45
  },
  {
    "date": "2017-02-09T05:00:00.000Z",
    "spot": 1146.15
  },
  {
    "date": "2017-01-31T05:00:00.000Z",
    "spot": 1161.6
  },
  {
    "date": "2017-01-20T05:00:00.000Z",
    "spot": 1169.13
  },
  {
    "date": "2017-01-11T05:00:00.000Z",
    "spot": 1196.35
  },
  {
    "date": "2017-01-02T05:00:00.000Z",
    "spot": 1207.93
  },
  {
    "date": "2016-12-22T05:00:00.000Z",
    "spot": 1199.15
  },
  {
    "date": "2016-12-13T05:00:00.000Z",
    "spot": 1166.57
  },
  {
    "date": "2016-12-02T05:00:00.000Z",
    "spot": 1172.5
  },
  {
    "date": "2016-11-23T05:00:00.000Z",
    "spot": 1176.35
  },
  {
    "date": "2016-11-14T05:00:00.000Z",
    "spot": 1171.9
  },
  {
    "date": "2016-11-03T04:00:00.000Z",
    "spot": 1141.63
  },
  {
    "date": "2016-10-25T04:00:00.000Z",
    "spot": 1133.4
  },
  {
    "date": "2016-10-14T04:00:00.000Z",
    "spot": 1133.4
  },
  {
    "date": "2016-10-05T04:00:00.000Z",
    "spot": 1113.57
  },
  {
    "date": "2016-09-26T04:00:00.000Z",
    "spot": 1107.95
  },
  {
    "date": "2016-09-15T04:00:00.000Z",
    "spot": 0
  },
  {
    "date": "2016-09-06T04:00:00.000Z",
    "spot": 1105.25
  },
  {
    "date": "2016-08-26T04:00:00.000Z",
    "spot": 1113.7
  },
  {
    "date": "2016-08-17T04:00:00.000Z",
    "spot": 1108.85
  },
  {
    "date": "2016-08-08T04:00:00.000Z",
    "spot": 1108.3
  },
  {
    "date": "2016-07-28T04:00:00.000Z",
    "spot": 1124.45
  },
  {
    "date": "2016-07-19T04:00:00.000Z",
    "spot": 1135.55
  },
  {
    "date": "2016-07-08T04:00:00.000Z",
    "spot": 1161.77
  },
  {
    "date": "2016-06-29T04:00:00.000Z",
    "spot": 1160.1
  },
  {
    "date": "2016-06-20T04:00:00.000Z",
    "spot": 1160.77
  },
  {
    "date": "2016-06-09T04:00:00.000Z",
    "spot": 1155.9
  },
  {
    "date": "2016-05-31T04:00:00.000Z",
    "spot": 1191.73
  },
  {
    "date": "2016-05-20T04:00:00.000Z",
    "spot": 1190.15
  },
  {
    "date": "2016-05-11T04:00:00.000Z",
    "spot": 1167.68
  },
  {
    "date": "2016-05-02T04:00:00.000Z",
    "spot": 1137.65
  },
  {
    "date": "2016-04-21T04:00:00.000Z",
    "spot": 1132.95
  },
  {
    "date": "2016-04-12T04:00:00.000Z",
    "spot": 1145.9
  },
  {
    "date": "2016-04-01T04:00:00.000Z",
    "spot": 1154.05
  },
  {
    "date": "2016-03-23T04:00:00.000Z",
    "spot": 1161.1
  },
  {
    "date": "2016-03-14T04:00:00.000Z",
    "spot": 1186.25
  },
  {
    "date": "2016-03-03T05:00:00.000Z",
    "spot": 1214.65
  },
  {
    "date": "2016-02-23T05:00:00.000Z",
    "spot": 1231.2
  },
  {
    "date": "2016-02-12T05:00:00.000Z",
    "spot": 1211.55
  },
  {
    "date": "2016-02-03T05:00:00.000Z",
    "spot": 1219.3
  },
  {
    "date": "2016-01-25T05:00:00.000Z",
    "spot": 1194.2
  },
  {
    "date": "2016-01-14T05:00:00.000Z",
    "spot": 1213.35
  },
  {
    "date": "2016-01-05T05:00:00.000Z",
    "spot": 1188.1
  },
  {
    "date": "2015-12-25T05:00:00.000Z",
    "spot": 1167.85
  },
  {
    "date": "2015-12-16T05:00:00.000Z",
    "spot": 1176.25
  },
  {
    "date": "2015-12-07T05:00:00.000Z",
    "spot": 1168.1
  },
  {
    "date": "2015-11-26T05:00:00.000Z",
    "spot": 1147.25
  },
  {
    "date": "2015-11-17T05:00:00.000Z",
    "spot": 1170.35
  },
  {
    "date": "2015-11-06T05:00:00.000Z",
    "spot": 1142
  },
  {
    "date": "2015-10-28T04:00:00.000Z",
    "spot": 1130.9
  },
  {
    "date": "2015-10-19T04:00:00.000Z",
    "spot": 1121.2
  },
  {
    "date": "2015-10-08T04:00:00.000Z",
    "spot": 1158.7
  },
  {
    "date": "2015-09-29T04:00:00.000Z",
    "spot": 1194.75
  },
  {
    "date": "2015-09-18T04:00:00.000Z",
    "spot": 1162.8
  },
  {
    "date": "2015-09-09T04:00:00.000Z",
    "spot": 1189.5
  },
  {
    "date": "2015-08-31T04:00:00.000Z",
    "spot": 1182.65
  },
  {
    "date": "2015-08-20T04:00:00.000Z",
    "spot": 1185.15
  },
  {
    "date": "2015-08-11T04:00:00.000Z",
    "spot": 1178.9
  },
  {
    "date": "2015-07-31T04:00:00.000Z",
    "spot": 1170.2
  },
  {
    "date": "2015-07-22T04:00:00.000Z",
    "spot": 1153.55
  },
  {
    "date": "2015-07-13T04:00:00.000Z",
    "spot": 1130.5
  },
  {
    "date": "2015-07-02T04:00:00.000Z",
    "spot": 1124.95
  },
  {
    "date": "2015-06-23T04:00:00.000Z",
    "spot": 1104.7
  },
  {
    "date": "2015-06-12T04:00:00.000Z",
    "spot": 1114.65
  },
  {
    "date": "2015-06-03T04:00:00.000Z",
    "spot": 1104.65
  },
  {
    "date": "2015-05-25T04:00:00.000Z",
    "spot": 1090.1
  },
  {
    "date": "2015-05-14T04:00:00.000Z",
    "spot": 1090.4
  },
  {
    "date": "2015-05-05T04:00:00.000Z",
    "spot": 1079.15
  },
  {
    "date": "2015-04-24T04:00:00.000Z",
    "spot": 1079.45
  },
  {
    "date": "2015-04-15T04:00:00.000Z",
    "spot": 1096.85
  },
  {
    "date": "2015-04-06T04:00:00.000Z",
    "spot": 1085.05
  },
  {
    "date": "2015-03-26T04:00:00.000Z",
    "spot": 1107.75
  },
  {
    "date": "2015-03-17T04:00:00.000Z",
    "spot": 1128.9
  },
  {
    "date": "2015-03-06T05:00:00.000Z",
    "spot": 1098.85
  },
  {
    "date": "2015-02-25T05:00:00.000Z",
    "spot": 1099.05
  },
  {
    "date": "2015-02-16T05:00:00.000Z",
    "spot": 1102.2
  },
  {
    "date": "2015-02-05T05:00:00.000Z",
    "spot": 1091.4
  },
  {
    "date": "2015-01-27T05:00:00.000Z",
    "spot": 1079.75
  },
  {
    "date": "2015-01-16T05:00:00.000Z",
    "spot": 1077.25
  },
  {
    "date": "2015-01-07T05:00:00.000Z",
    "spot": 1099.93
  },
  {
    "date": "2014-12-29T05:00:00.000Z",
    "spot": 1097.7
  },
  {
    "date": "2014-12-18T05:00:00.000Z",
    "spot": 1102.3
  },
  {
    "date": "2014-12-09T05:00:00.000Z",
    "spot": 1107.8
  },
  {
    "date": "2014-11-28T05:00:00.000Z",
    "spot": 1108.05
  },
  {
    "date": "2014-11-19T05:00:00.000Z",
    "spot": 1106.35
  },
  {
    "date": "2014-11-10T05:00:00.000Z",
    "spot": 1085
  },
  {
    "date": "2014-10-30T04:00:00.000Z",
    "spot": 1055.6
  },
  {
    "date": "2014-10-21T04:00:00.000Z",
    "spot": 1054.7
  },
  {
    "date": "2014-10-10T04:00:00.000Z",
    "spot": 1070.45
  },
  {
    "date": "2014-10-01T04:00:00.000Z",
    "spot": 1062.65
  },
  {
    "date": "2014-09-22T04:00:00.000Z",
    "spot": 1040.8
  },
  {
    "date": "2014-09-11T04:00:00.000Z",
    "spot": 1035.95
  },
  {
    "date": "2014-09-02T04:00:00.000Z",
    "spot": 1018.25
  },
  {
    "date": "2014-08-22T04:00:00.000Z",
    "spot": 1017.75
  },
  {
    "date": "2014-08-13T04:00:00.000Z",
    "spot": 1029.4
  },
  {
    "date": "2014-08-04T04:00:00.000Z",
    "spot": 1033.55
  },
  {
    "date": "2014-07-24T04:00:00.000Z",
    "spot": 1028.7
  },
  {
    "date": "2014-07-15T04:00:00.000Z",
    "spot": 1027.35
  },
  {
    "date": "2014-07-04T04:00:00.000Z",
    "spot": 1008.9
  },
  {
    "date": "2014-06-25T04:00:00.000Z",
    "spot": 1020.95
  },
  {
    "date": "2014-06-16T04:00:00.000Z",
    "spot": 1019.9
  },
  {
    "date": "2014-06-05T04:00:00.000Z",
    "spot": 1020.45
  },
  {
    "date": "2014-05-27T04:00:00.000Z",
    "spot": 1023.17
  },
  {
    "date": "2014-05-16T04:00:00.000Z",
    "spot": 1024.13
  },
  {
    "date": "2014-05-07T04:00:00.000Z",
    "spot": 1022.65
  },
  {
    "date": "2014-04-28T04:00:00.000Z",
    "spot": 1035.18
  },
  {
    "date": "2014-04-17T04:00:00.000Z",
    "spot": 1038.82
  },
  {
    "date": "2014-04-08T04:00:00.000Z",
    "spot": 1052.27
  },
  {
    "date": "2014-03-28T04:00:00.000Z",
    "spot": 1069.2
  },
  {
    "date": "2014-03-19T04:00:00.000Z",
    "spot": 1070.1
  },
  {
    "date": "2014-03-10T04:00:00.000Z",
    "spot": 1066.47
  },
  {
    "date": "2014-02-27T05:00:00.000Z",
    "spot": 1069
  },
  {
    "date": "2014-02-18T05:00:00.000Z",
    "spot": 1066.25
  },
  {
    "date": "2014-02-07T05:00:00.000Z",
    "spot": 1074.32
  },
  {
    "date": "2014-01-29T05:00:00.000Z",
    "spot": 1070.3
  },
  {
    "date": "2014-01-20T05:00:00.000Z",
    "spot": 1063.55
  },
  {
    "date": "2014-01-09T05:00:00.000Z",
    "spot": 1062.68
  },
  {
    "date": "2013-12-31T05:00:00.000Z",
    "spot": 0
  },
  {
    "date": "2013-12-20T05:00:00.000Z",
    "spot": 1061.35
  },
  {
    "date": "2013-12-11T05:00:00.000Z",
    "spot": 1052.23
  },
  {
    "date": "2013-12-02T05:00:00.000Z",
    "spot": 1057.13
  },
  {
    "date": "2013-11-21T05:00:00.000Z",
    "spot": 1062.75
  },
  {
    "date": "2013-11-12T05:00:00.000Z",
    "spot": 1071.38
  },
  {
    "date": "2013-11-01T04:00:00.000Z",
    "spot": 1060.8
  },
  {
    "date": "2013-10-23T04:00:00.000Z",
    "spot": 1056.03
  },
  {
    "date": "2013-10-14T04:00:00.000Z",
    "spot": 1071.5
  },
  {
    "date": "2013-10-03T04:00:00.000Z",
    "spot": 0
  },
  {
    "date": "2013-09-24T04:00:00.000Z",
    "spot": 1072.4
  },
  {
    "date": "2013-09-13T04:00:00.000Z",
    "spot": 1086.9
  },
  {
    "date": "2013-09-04T04:00:00.000Z",
    "spot": 1094.55
  },
  {
    "date": "2013-08-26T04:00:00.000Z",
    "spot": 1112.65
  },
  {
    "date": "2013-08-15T04:00:00.000Z",
    "spot": 0
  },
  {
    "date": "2013-08-06T04:00:00.000Z",
    "spot": 1115.48
  },
  {
    "date": "2013-07-26T04:00:00.000Z",
    "spot": 1111.43
  },
  {
    "date": "2013-07-17T04:00:00.000Z",
    "spot": 1121.57
  },
  {
    "date": "2013-07-08T04:00:00.000Z",
    "spot": 1152.17
  },
  {
    "date": "2013-06-27T04:00:00.000Z",
    "spot": 1149.68
  },
  {
    "date": "2013-06-18T04:00:00.000Z",
    "spot": 1131
  },
  {
    "date": "2013-06-07T04:00:00.000Z",
    "spot": 1116.85
  },
  {
    "date": "2013-05-29T04:00:00.000Z",
    "spot": 1132.95
  },
  {
    "date": "2013-05-20T04:00:00.000Z",
    "spot": 1116.68
  },
  {
    "date": "2013-05-09T04:00:00.000Z",
    "spot": 1091.28
  },
  {
    "date": "2013-04-30T04:00:00.000Z",
    "spot": 1101.1
  },
  {
    "date": "2013-04-19T04:00:00.000Z",
    "spot": 1116.2
  },
  {
    "date": "2013-04-10T04:00:00.000Z",
    "spot": 1136.4
  },
  {
    "date": "2013-04-01T04:00:00.000Z",
    "spot": 1114.68
  },
  {
    "date": "2013-03-21T04:00:00.000Z",
    "spot": 1116.05
  }
]
